Workbook

Sheet Product Sales Summary
F3: SALES QUANTITY | K3: SALES VALUE | P3: AVERAGE DISCOUNT
D4: Average unit price | E4: Average unit cost | F4: Mon | G4: Tue | H4: Wed | I4: Thu | J4: Fri | K4: Mon | L4: Tue | M4: Wed | N4: Thu | O4: Fri | P4: Mon | Q4: Tue | R4: Wed | S4: Thu | T4: Fri
C5: Cookware | D5: =AVERAGEIFS('Sales Orders Sheet'!$O:$O,'Sales Orders Sheet'!$W:$W,C5) | E5: =AVERAGEIFS('Sales Orders Sheet'!$P:$P,'Sales Orders Sheet'!$W:$W,C5) | F5: =SUMIFS('Sales Orders Sheet'!$M:$M,'Sales Orders Sheet'!$W:$W,C5,'Sales Orders Sheet'!$Q:$Q,F$4) | G5: =SUMIFS('Sales Orders Sheet'!$M:$M,'Sales Orders Sheet'!$W:$W,C5,'Sales Orders Sheet'!$Q:$Q,G$4) | H5: =SUMIFS('Sales Orders Sheet'!$M:$M,'Sales Orders Sheet'!$W:$W,C5,'Sales Orders Sheet'!$Q:$Q,H$4) | I5: =SUMIFS('Sales Orders Sheet'!$M:$M,'Sales Orders Sheet'!$W:$W,C5,'Sales Orders Sheet'!$Q:$Q,I$4) | J5: =SUMIFS('Sales Orders Sheet'!$M:$M,'Sales Orders Sheet'!$W:$W,C5,'Sales Orders Sheet'!$Q:$Q,J$4) | K5: =SUMIFS('Sales Orders Sheet'!$T:$T,'Sales Orders Sheet'!$W:$W,C5,'Sales Orders Sheet'!$Q:$Q,K$4) | L5: =SUMIFS('Sales Orders Sheet'!$T:$T,'Sales Orders Sheet'!$W:$W,C5,'Sales Orders Sheet'!$Q:$Q,L$4) | M5: =SUMIFS('Sales Orders Sheet'!$T:$T,'Sales Orders Sheet'!$W:$W,C5,'Sales Orders Sheet'!$Q:$Q,M$4) | N5: =SUMIFS('Sales Orders Sheet'!$T:$T,'Sales Orders Sheet'!$W:$W,C5,'Sales Orders Sheet'!$Q:$Q,N$4) | O5: =SUMIFS('Sales Orders Sheet'!$T:$T,'Sales Orders Sheet'!$W:$W,C5,'Sales Orders Sheet'!$Q:$Q,O$4) | P5: =AVERAGEIFS('Sales Orders Sheet'!$N:$N,'Sales Orders Sheet'!$W:$W,C5,'Sales Orders Sheet'!$Q:$Q,P$4) | Q5: =AVERAGEIFS('Sales Orders Sheet'!$N:$N,'Sales Orders Sheet'!$W:$W,C5,'Sales Orders Sheet'!$Q:$Q,Q$4) | R5: =AVERAGEIFS('Sales Orders Sheet'!$N:$N,'Sales Orders Sheet'!$W:$W,C5,'Sales Orders Sheet'!$Q:$Q,R$4) | S5: =AVERAGEIFS('Sales Orders Sheet'!$N:$N,'Sales Orders Sheet'!$W:$W,C5,'Sales Orders Sheet'!$Q:$Q,S$4) | T5: =AVERAGEIFS('Sales Orders Sheet'!$N:$N,'Sales Orders Sheet'!$W:$W,C5,'Sales Orders Sheet'!$Q:$Q,T$4)
C6: Photo Frames | D6: =AVERAGEIFS('Sales Orders Sheet'!$O:$O,'Sales Orders Sheet'!$W:$W,C6) | E6: =AVERAGEIFS('Sales Orders Sheet'!$P:$P,'Sales Orders Sheet'!$W:$W,C6) | F6: =SUMIFS('Sales Orders Sheet'!$M:$M,'Sales Orders Sheet'!$W:$W,C6,'Sales Orders Sheet'!$Q:$Q,F$4) | G6: =SUMIFS('Sales Orders Sheet'!$M:$M,'Sales Orders Sheet'!$W:$W,C6,'Sales Orders Sheet'!$Q:$Q,G$4) | H6: =SUMIFS('Sales Orders Sheet'!$M:$M,'Sales Orders Sheet'!$W:$W,C6,'Sales Orders Sheet'!$Q:$Q,H$4) | I6: =SUMIFS('Sales Orders Sheet'!$M:$M,'Sales Orders Sheet'!$W:$W,C6,'Sales Orders Sheet'!$Q:$Q,I$4) | J6: =SUMIFS('Sales Orders Sheet'!$M:$M,'Sales Orders Sheet'!$W:$W,C6,'Sales Orders Sheet'!$Q:$Q,J$4) | K6: =SUMIFS('Sales Orders Sheet'!$T:$T,'Sales Orders Sheet'!$W:$W,C6,'Sales Orders Sheet'!$Q:$Q,K$4) | L6: =SUMIFS('Sales Orders Sheet'!$T:$T,'Sales Orders Sheet'!$W:$W,C6,'Sales Orders Sheet'!$Q:$Q,L$4) | M6: =SUMIFS('Sales Orders Sheet'!$T:$T,'Sales Orders Sheet'!$W:$W,C6,'Sales Orders Sheet'!$Q:$Q,M$4) | N6: =SUMIFS('Sales Orders Sheet'!$T:$T,'Sales Orders Sheet'!$W:$W,C6,'Sales Orders Sheet'!$Q:$Q,N$4) | O6: =SUMIFS('Sales Orders Sheet'!$T:$T,'Sales Orders Sheet'!$W:$W,C6,'Sales Orders Sheet'!$Q:$Q,O$4) | P6: =AVERAGEIFS('Sales Orders Sheet'!$N:$N,'Sales Orders Sheet'!$W:$W,C6,'Sales Orders Sheet'!$Q:$Q,P$4) | Q6: =AVERAGEIFS('Sales Orders Sheet'!$N:$N,'Sales Orders Sheet'!$W:$W,C6,'Sales Orders Sheet'!$Q:$Q,Q$4) | R6: =AVERAGEIFS('Sales Orders Sheet'!$N:$N,'Sales Orders Sheet'!$W:$W,C6,'Sales Orders Sheet'!$Q:$Q,R$4) | S6: =AVERAGEIFS('Sales Orders Sheet'!$N:$N,'Sales Orders Sheet'!$W:$W,C6,'Sales Orders Sheet'!$Q:$Q,S$4) | T6: =AVERAGEIFS('Sales Orders Sheet'!$N:$N,'Sales Orders Sheet'!$W:$W,C6,'Sales Orders Sheet'!$Q:$Q,T$4)
C7: Table Lamps | D7: =AVERAGEIFS('Sales Orders Sheet'!$O:$O,'Sales Orders Sheet'!$W:$W,C7) | E7: =AVERAGEIFS('Sales Orders Sheet'!$P:$P,'Sales Orders Sheet'!$W:$W,C7) | F7: =SUMIFS('Sales Orders Sheet'!$M:$M,'Sales Orders Sheet'!$W:$W,C7,'Sales Orders Sheet'!$Q:$Q,F$4) | G7: =SUMIFS('Sales Orders Sheet'!$M:$M,'Sales Orders Sheet'!$W:$W,C7,'Sales Orders Sheet'!$Q:$Q,G$4) | H7: =SUMIFS('Sales Orders Sheet'!$M:$M,'Sales Orders Sheet'!$W:$W,C7,'Sales Orders Sheet'!$Q:$Q,H$4) | I7: =SUMIFS('Sales Orders Sheet'!$M:$M,'Sales Orders Sheet'!$W:$W,C7,'Sales Orders Sheet'!$Q:$Q,I$4) | J7: =SUMIFS('Sales Orders Sheet'!$M:$M,'Sales Orders Sheet'!$W:$W,C7,'Sales Orders Sheet'!$Q:$Q,J$4) | K7: =SUMIFS('Sales Orders Sheet'!$T:$T,'Sales Orders Sheet'!$W:$W,C7,'Sales Orders Sheet'!$Q:$Q,K$4) | L7: =SUMIFS('Sales Orders Sheet'!$T:$T,'Sales Orders Sheet'!$W:$W,C7,'Sales Orders Sheet'!$Q:$Q,L$4) | M7: =SUMIFS('Sales Orders Sheet'!$T:$T,'Sales Orders Sheet'!$W:$W,C7,'Sales Orders Sheet'!$Q:$Q,M$4) | N7: =SUMIFS('Sales Orders Sheet'!$T:$T,'Sales Orders Sheet'!$W:$W,C7,'Sales Orders Sheet'!$Q:$Q,N$4) | O7: =SUMIFS('Sales Orders Sheet'!$T:$T,'Sales Orders Sheet'!$W:$W,C7,'Sales Orders Sheet'!$Q:$Q,O$4) | P7: =AVERAGEIFS('Sales Orders Sheet'!$N:$N,'Sales Orders Sheet'!$W:$W,C7,'Sales Orders Sheet'!$Q:$Q,P$4) | Q7: =AVERAGEIFS('Sales Orders Sheet'!$N:$N,'Sales Orders Sheet'!$W:$W,C7,'Sales Orders Sheet'!$Q:$Q,Q$4) | R7: =AVERAGEIFS('Sales Orders Sheet'!$N:$N,'Sales Orders Sheet'!$W:$W,C7,'Sales Orders Sheet'!$Q:$Q,R$4) | S7: =AVERAGEIFS('Sales Orders Sheet'!$N:$N,'Sales Orders Sheet'!$W:$W,C7,'Sales Orders Sheet'!$Q:$Q,S$4) | T7: =AVERAGEIFS('Sales Orders Sheet'!$N:$N,'Sales Orders Sheet'!$W:$W,C7,'Sales Orders Sheet'!$Q:$Q,T$4)
C8: Serveware | D8: =AVERAGEIFS('Sales Orders Sheet'!$O:$O,'Sales Orders Sheet'!$W:$W,C8) | E8: =AVERAGEIFS('Sales Orders Sheet'!$P:$P,'Sales Orders Sheet'!$W:$W,C8) | F8: =SUMIFS('Sales Orders Sheet'!$M:$M,'Sales Orders Sheet'!$W:$W,C8,'Sales Orders Sheet'!$Q:$Q,F$4) | G8: =SUMIFS('Sales Orders Sheet'!$M:$M,'Sales Orders Sheet'!$W:$W,C8,'Sales Orders Sheet'!$Q:$Q,G$4) | H8: =SUMIFS('Sales Orders Sheet'!$M:$M,'Sales Orders Sheet'!$W:$W,C8,'Sales Orders Sheet'!$Q:$Q,H$4) | I8: =SUMIFS('Sales Orders Sheet'!$M:$M,'Sales Orders Sheet'!$W:$W,C8,'Sales Orders Sheet'!$Q:$Q,I$4) | J8: =SUMIFS('Sales Orders Sheet'!$M:$M,'Sales Orders Sheet'!$W:$W,C8,'Sales Orders Sheet'!$Q:$Q,J$4) | K8: =SUMIFS('Sales Orders Sheet'!$T:$T,'Sales Orders Sheet'!$W:$W,C8,'Sales Orders Sheet'!$Q:$Q,K$4) | L8: =SUMIFS('Sales Orders Sheet'!$T:$T,'Sales Orders Sheet'!$W:$W,C8,'Sales Orders Sheet'!$Q:$Q,L$4) | M8: =SUMIFS('Sales Orders Sheet'!$T:$T,'Sales Orders Sheet'!$W:$W,C8,'Sales Orders Sheet'!$Q:$Q,M$4) | N8: =SUMIFS('Sales Orders Sheet'!$T:$T,'Sales Orders Sheet'!$W:$W,C8,'Sales Orders Sheet'!$Q:$Q,N$4) | O8: =SUMIFS('Sales Orders Sheet'!$T:$T,'Sales Orders Sheet'!$W:$W,C8,'Sales Orders Sheet'!$Q:$Q,O$4) | P8: =AVERAGEIFS('Sales Orders Sheet'!$N:$N,'Sales Orders Sheet'!$W:$W,C8,'Sales Orders Sheet'!$Q:$Q,P$4) | Q8: =AVERAGEIFS('Sales Orders Sheet'!$N:$N,'Sales Orders Sheet'!$W:$W,C8,'Sales Orders Sheet'!$Q:$Q,Q$4) | R8: =AVERAGEIFS('Sales Orders Sheet'!$N:$N,'Sales Orders Sheet'!$W:$W,C8,'Sales Orders Sheet'!$Q:$Q,R$4) | S8: =AVERAGEIFS('Sales Orders Sheet'!$N:$N,'Sales Orders Sheet'!$W:$W,C8,'Sales Orders Sheet'!$Q:$Q,S$4) | T8: =AVERAGEIFS('Sales Orders Sheet'!$N:$N,'Sales Orders Sheet'!$W:$W,C8,'Sales Orders Sheet'!$Q:$Q,T$4)
C9: Bathroom Furniture | D9: =AVERAGEIFS('Sales Orders Sheet'!$O:$O,'Sales Orders Sheet'!$W:$W,C9) | E9: =AVERAGEIFS('Sales Orders Sheet'!$P:$P,'Sales Orders Sheet'!$W:$W,C9) | F9: =SUMIFS('Sales Orders Sheet'!$M:$M,'Sales Orders Sheet'!$W:$W,C9,'Sales Orders Sheet'!$Q:$Q,F$4) | G9: =SUMIFS('Sales Orders Sheet'!$M:$M,'Sales Orders Sheet'!$W:$W,C9,'Sales Orders Sheet'!$Q:$Q,G$4) | H9: =SUMIFS('Sales Orders Sheet'!$M:$M,'Sales Orders Sheet'!$W:$W,C9,'Sales Orders Sheet'!$Q:$Q,H$4) | I9: =SUMIFS('Sales Orders Sheet'!$M:$M,'Sales Orders Sheet'!$W:$W,C9,'Sales Orders Sheet'!$Q:$Q,I$4) | J9: =SUMIFS('Sales Orders Sheet'!$M:$M,'Sales Orders Sheet'!$W:$W,C9,'Sales Orders Sheet'!$Q:$Q,J$4) | K9: =SUMIFS('Sales Orders Sheet'!$T:$T,'Sales Orders Sheet'!$W:$W,C9,'Sales Orders Sheet'!$Q:$Q,K$4) | L9: =SUMIFS('Sales Orders Sheet'!$T:$T,'Sales Orders Sheet'!$W:$W,C9,'Sales Orders Sheet'!$Q:$Q,L$4) | M9: =SUMIFS('Sales Orders Sheet'!$T:$T,'Sales Orders Sheet'!$W:$W,C9,'Sales Orders Sheet'!$Q:$Q,M$4) | N9: =SUMIFS('Sales Orders Sheet'!$T:$T,'Sales Orders Sheet'!$W:$W,C9,'Sales Orders Sheet'!$Q:$Q,N$4) | O9: =SUMIFS('Sales Orders Sheet'!$T:$T,'Sales Orders Sheet'!$W:$W,C9,'Sales Orders Sheet'!$Q:$Q,O$4) | P9: =AVERAGEIFS('Sales Orders Sheet'!$N:$N,'Sales Orders Sheet'!$W:$W,C9,'Sales Orders Sheet'!$Q:$Q,P$4) | Q9: =AVERAGEIFS('Sales Orders Sheet'!$N:$N,'Sales Orders Sheet'!$W:$W,C9,'Sales Orders Sheet'!$Q:$Q,Q$4) | R9: =AVERAGEIFS('Sales Orders Sheet'!$N:$N,'Sales Orders Sheet'!$W:$W,C9,'Sales Orders Sheet'!$Q:$Q,R$4) | S9: =AVERAGEIFS('Sales Orders Sheet'!$N:$N,'Sales Orders Sheet'!$W:$W,C9,'Sales Orders Sheet'!$Q:$Q,S$4) | T9: =AVERAGEIFS('Sales Orders Sheet'!$N:$N,'Sales Orders Sheet'!$W:$W,C9,'Sales Orders Sheet'!$Q:$Q,T$4)
C10: Computers | D10: =AVERAGEIFS('Sales Orders Sheet'!$O:$O,'Sales Orders Sheet'!$W:$W,C10) | E10: =AVERAGEIFS('Sales Orders Sheet'!$P:$P,'Sales Orders Sheet'!$W:$W,C10) | F10: =SUMIFS('Sales Orders Sheet'!$M:$M,'Sales Orders Sheet'!$W:$W,C10,'Sales Orders Sheet'!$Q:$Q,F$4) | G10: =SUMIFS('Sales Orders Sheet'!$M:$M,'Sales Orders Sheet'!$W:$W,C10,'Sales Orders Sheet'!$Q:$Q,G$4) | H10: =SUMIFS('Sales Orders Sheet'!$M:$M,'Sales Orders Sheet'!$W:$W,C10,'Sales Orders Sheet'!$Q:$Q,H$4) | I10: =SUMIFS('Sales Orders Sheet'!$M:$M,'Sales Orders Sheet'!$W:$W,C10,'Sales Orders Sheet'!$Q:$Q,I$4) | J10: =SUMIFS('Sales Orders Sheet'!$M:$M,'Sales Orders Sheet'!$W:$W,C10,'Sales Orders Sheet'!$Q:$Q,J$4) | K10: =SUMIFS('Sales Orders Sheet'!$T:$T,'Sales Orders Sheet'!$W:$W,C10,'Sales Orders Sheet'!$Q:$Q,K$4) | L10: =SUMIFS('Sales Orders Sheet'!$T:$T,'Sales Orders Sheet'!$W:$W,C10,'Sales Orders Sheet'!$Q:$Q,L$4) | M10: =SUMIFS('Sales Orders Sheet'!$T:$T,'Sales Orders Sheet'!$W:$W,C10,'Sales Orders Sheet'!$Q:$Q,M$4) | N10: =SUMIFS('Sales Orders Sheet'!$T:$T,'Sales Orders Sheet'!$W:$W,C10,'Sales Orders Sheet'!$Q:$Q,N$4) | O10: =SUMIFS('Sales Orders Sheet'!$T:$T,'Sales Orders Sheet'!$W:$W,C10,'Sales Orders Sheet'!$Q:$Q,O$4) | P10: =AVERAGEIFS('Sales Orders Sheet'!$N:$N,'Sales Orders Sheet'!$W:$W,C10,'Sales Orders Sheet'!$Q:$Q,P$4) | Q10: =AVERAGEIFS('Sales Orders Sheet'!$N:$N,'Sales Orders Sheet'!$W:$W,C10,'Sales Orders Sheet'!$Q:$Q,Q$4) | R10: =AVERAGEIFS('Sales Orders Sheet'!$N:$N,'Sales Orders Sheet'!$W:$W,C10,'Sales Orders Sheet'!$Q:$Q,R$4) | S10: =AVERAGEIFS('Sales Orders Sheet'!$N:$N,'Sales Orders Sheet'!$W:$W,C10,'Sales Orders Sheet'!$Q:$Q,S$4) | T10: =AVERAGEIFS('Sales Orders Sheet'!$N:$N,'Sales Orders Sheet'!$W:$W,C10,'Sales Orders Sheet'!$Q:$Q,T$4)
C11: Dinnerware | D11: =AVERAGEIFS('Sales Orders Sheet'!$O:$O,'Sales Orders Sheet'!$W:$W,C11) | E11: =AVERAGEIFS('Sales Orders Sheet'!$P:$P,'Sales Orders Sheet'!$W:$W,C11) | F11: =SUMIFS('Sales Orders Sheet'!$M:$M,'Sales Orders Sheet'!$W:$W,C11,'Sales Orders Sheet'!$Q:$Q,F$4) | G11: =SUMIFS('Sales Orders Sheet'!$M:$M,'Sales Orders Sheet'!$W:$W,C11,'Sales Orders Sheet'!$Q:$Q,G$4) | H11: =SUMIFS('Sales Orders Sheet'!$M:$M,'Sales Orders Sheet'!$W:$W,C11,'Sales Orders Sheet'!$Q:$Q,H$4) | I11: =SUMIFS('Sales Orders Sheet'!$M:$M,'Sales Orders Sheet'!$W:$W,C11,'Sales Orders Sheet'!$Q:$Q,I$4) | J11: =SUMIFS('Sales Orders Sheet'!$M:$M,'Sales Orders Sheet'!$W:$W,C11,'Sales Orders Sheet'!$Q:$Q,J$4) | K11: =SUMIFS('Sales Orders Sheet'!$T:$T,'Sales Orders Sheet'!$W:$W,C11,'Sales Orders Sheet'!$Q:$Q,K$4) | L11: =SUMIFS('Sales Orders Sheet'!$T:$T,'Sales Orders Sheet'!$W:$W,C11,'Sales Orders Sheet'!$Q:$Q,L$4) | M11: =SUMIFS('Sales Orders Sheet'!$T:$T,'Sales Orders Sheet'!$W:$W,C11,'Sales Orders Sheet'!$Q:$Q,M$4) | N11: =SUMIFS('Sales Orders Sheet'!$T:$T,'Sales Orders Sheet'!$W:$W,C11,'Sales Orders Sheet'!$Q:$Q,N$4) | O11: =SUMIFS('Sales Orders Sheet'!$T:$T,'Sales Orders Sheet'!$W:$W,C11,'Sales Orders Sheet'!$Q:$Q,O$4) | P11: =AVERAGEIFS('Sales Orders Sheet'!$N:$N,'Sales Orders Sheet'!$W:$W,C11,'Sales Orders Sheet'!$Q:$Q,P$4) | Q11: =AVERAGEIFS('Sales Orders Sheet'!$N:$N,'Sales Orders Sheet'!$W:$W,C11,'Sales Orders Sheet'!$Q:$Q,Q$4) | R11: =AVERAGEIFS('Sales Orders Sheet'!$N:$N,'Sales Orders Sheet'!$W:$W,C11,'Sales Orders Sheet'!$Q:$Q,R$4) | S11: =AVERAGEIFS('Sales Orders Sheet'!$N:$N,'Sales Orders Sheet'!$W:$W,C11,'Sales Orders Sheet'!$Q:$Q,S$4) | T11: =AVERAGEIFS('Sales Orders Sheet'!$N:$N,'Sales Orders Sheet'!$W:$W,C11,'Sales Orders Sheet'!$Q:$Q,T$4)
C12: Cocktail Glasses | D12: =AVERAGEIFS('Sales Orders Sheet'!$O:$O,'Sales Orders Sheet'!$W:$W,C12) | E12: =AVERAGEIFS('Sales Orders Sheet'!$P:$P,'Sales Orders Sheet'!$W:$W,C12) | F12: =SUMIFS('Sales Orders Sheet'!$M:$M,'Sales Orders Sheet'!$W:$W,C12,'Sales Orders Sheet'!$Q:$Q,F$4) | G12: =SUMIFS('Sales Orders Sheet'!$M:$M,'Sales Orders Sheet'!$W:$W,C12,'Sales Orders Sheet'!$Q:$Q,G$4) | H12: =SUMIFS('Sales Orders Sheet'!$M:$M,'Sales Orders Sheet'!$W:$W,C12,'Sales Orders Sheet'!$Q:$Q,H$4) | I12: =SUMIFS('Sales Orders Sheet'!$M:$M,'Sales Orders Sheet'!$W:$W,C12,'Sales Orders Sheet'!$Q:$Q,I$4) | J12: =SUMIFS('Sales Orders Sheet'!$M:$M,'Sales Orders Sheet'!$W:$W,C12,'Sales Orders Sheet'!$Q:$Q,J$4) | K12: =SUMIFS('Sales Orders Sheet'!$T:$T,'Sales Orders Sheet'!$W:$W,C12,'Sales Orders Sheet'!$Q:$Q,K$4) | L12: =SUMIFS('Sales Orders Sheet'!$T:$T,'Sales Orders Sheet'!$W:$W,C12,'Sales Orders Sheet'!$Q:$Q,L$4) | M12: =SUMIFS('Sales Orders Sheet'!$T:$T,'Sales Orders Sheet'!$W:$W,C12,'Sales Orders Sheet'!$Q:$Q,M$4) | N12: =SUMIFS('Sales Orders Sheet'!$T:$T,'Sales Orders Sheet'!$W:$W,C12,'Sales Orders Sheet'!$Q:$Q,N$4) | O12: =SUMIFS('Sales Orders Sheet'!$T:$T,'Sales Orders Sheet'!$W:$W,C12,'Sales Orders Sheet'!$Q:$Q,O$4) | P12: =AVERAGEIFS('Sales Orders Sheet'!$N:$N,'Sales Orders Sheet'!$W:$W,C12,'Sales Orders Sheet'!$Q:$Q,P$4) | Q12: =AVERAGEIFS('Sales Orders Sheet'!$N:$N,'Sales Orders Sheet'!$W:$W,C12,'Sales Orders Sheet'!$Q:$Q,Q$4) | R12: =AVERAGEIFS('Sales Orders Sheet'!$N:$N,'Sales Orders Sheet'!$W:$W,C12,'Sales Orders Sheet'!$Q:$Q,R$4) | S12: =AVERAGEIFS('Sales Orders Sheet'!$N:$N,'Sales Orders Sheet'!$W:$W,C12,'Sales Orders Sheet'!$Q:$Q,S$4) | T12: =AVERAGEIFS('Sales Orders Sheet'!$N:$N,'Sales Orders Sheet'!$W:$W,C12,'Sales Orders Sheet'!$Q:$Q,T$4)
C13: Baseball | D13: =AVERAGEIFS('Sales Orders Sheet'!$O:$O,'Sales Orders Sheet'!$W:$W,C13) | E13: =AVERAGEIFS('Sales Orders Sheet'!$P:$P,'Sales Orders Sheet'!$W:$W,C13) | F13: =SUMIFS('Sales Orders Sheet'!$M:$M,'Sales Orders Sheet'!$W:$W,C13,'Sales Orders Sheet'!$Q:$Q,F$4) | G13: =SUMIFS('Sales Orders Sheet'!$M:$M,'Sales Orders Sheet'!$W:$W,C13,'Sales Orders Sheet'!$Q:$Q,G$4) | H13: =SUMIFS('Sales Orders Sheet'!$M:$M,'Sales Orders Sheet'!$W:$W,C13,'Sales Orders Sheet'!$Q:$Q,H$4) | I13: =SUMIFS('Sales Orders Sheet'!$M:$M,'Sales Orders Sheet'!$W:$W,C13,'Sales Orders Sheet'!$Q:$Q,I$4) | J13: =SUMIFS('Sales Orders Sheet'!$M:$M,'Sales Orders Sheet'!$W:$W,C13,'Sales Orders Sheet'!$Q:$Q,J$4) | K13: =SUMIFS('Sales Orders Sheet'!$T:$T,'Sales Orders Sheet'!$W:$W,C13,'Sales Orders Sheet'!$Q:$Q,K$4) | L13: =SUMIFS('Sales Orders Sheet'!$T:$T,'Sales Orders Sheet'!$W:$W,C13,'Sales Orders Sheet'!$Q:$Q,L$4) | M13: =SUMIFS('Sales Orders Sheet'!$T:$T,'Sales Orders Sheet'!$W:$W,C13,'Sales Orders Sheet'!$Q:$Q,M$4) | N13: =SUMIFS('Sales Orders Sheet'!$T:$T,'Sales Orders Sheet'!$W:$W,C13,'Sales Orders Sheet'!$Q:$Q,N$4) | O13: =SUMIFS('Sales Orders Sheet'!$T:$T,'Sales Orders Sheet'!$W:$W,C13,'Sales Orders Sheet'!$Q:$Q,O$4) | P13: =AVERAGEIFS('Sales Orders Sheet'!$N:$N,'Sales Orders Sheet'!$W:$W,C13,'Sales Orders Sheet'!$Q:$Q,P$4) | Q13: =AVERAGEIFS('Sales Orders Sheet'!$N:$N,'Sales Orders Sheet'!$W:$W,C13,'Sales Orders Sheet'!$Q:$Q,Q$4) | R13: =AVERAGEIFS('Sales Orders Sheet'!$N:$N,'Sales Orders Sheet'!$W:$W,C13,'Sales Orders Sheet'!$Q:$Q,R$4) | S13: =AVERAGEIFS('Sales Orders Sheet'!$N:$N,'Sales Orders Sheet'!$W:$W,C13,'Sales Orders Sheet'!$Q:$Q,S$4) | T13: =AVERAGEIFS('Sales Orders Sheet'!$N:$N,'Sales Orders Sheet'!$W:$W,C13,'Sales Orders Sheet'!$Q:$Q,T$4)
C14: Blankets | D14: =AVERAGEIFS('Sales Orders Sheet'!$O:$O,'Sales Orders Sheet'!$W:$W,C14) | E14: =AVERAGEIFS('Sales Orders Sheet'!$P:$P,'Sales Orders Sheet'!$W:$W,C14) | F14: =SUMIFS('Sales Orders Sheet'!$M:$M,'Sales Orders Sheet'!$W:$W,C14,'Sales Orders Sheet'!$Q:$Q,F$4) | G14: =SUMIFS('Sales Orders Sheet'!$M:$M,'Sales Orders Sheet'!$W:$W,C14,'Sales Orders Sheet'!$Q:$Q,G$4) | H14: =SUMIFS('Sales Orders Sheet'!$M:$M,'Sales Orders Sheet'!$W:$W,C14,'Sales Orders Sheet'!$Q:$Q,H$4) | I14: =SUMIFS('Sales Orders Sheet'!$M:$M,'Sales Orders Sheet'!$W:$W,C14,'Sales Orders Sheet'!$Q:$Q,I$4) | J14: =SUMIFS('Sales Orders Sheet'!$M:$M,'Sales Orders Sheet'!$W:$W,C14,'Sales Orders Sheet'!$Q:$Q,J$4) | K14: =SUMIFS('Sales Orders Sheet'!$T:$T,'Sales Orders Sheet'!$W:$W,C14,'Sales Orders Sheet'!$Q:$Q,K$4) | L14: =SUMIFS('Sales Orders Sheet'!$T:$T,'Sales Orders Sheet'!$W:$W,C14,'Sales Orders Sheet'!$Q:$Q,L$4) | M14: =SUMIFS('Sales Orders Sheet'!$T:$T,'Sales Orders Sheet'!$W:$W,C14,'Sales Orders Sheet'!$Q:$Q,M$4) | N14: =SUMIFS('Sales Orders Sheet'!$T:$T,'Sales Orders Sheet'!$W:$W,C14,'Sales Orders Sheet'!$Q:$Q,N$4) | O14: =SUMIFS('Sales Orders Sheet'!$T:$T,'Sales Orders Sheet'!$W:$W,C14,'Sales Orders Sheet'!$Q:$Q,O$4) | P14: =AVERAGEIFS('Sales Orders Sheet'!$N:$N,'Sales Orders Sheet'!$W:$W,C14,'Sales Orders Sheet'!$Q:$Q,P$4) | Q14: =AVERAGEIFS('Sales Orders Sheet'!$N:$N,'Sales Orders Sheet'!$W:$W,C14,'Sales Orders Sheet'!$Q:$Q,Q$4) | R14: =AVERAGEIFS('Sales Orders Sheet'!$N:$N,'Sales Orders Sheet'!$W:$W,C14,'Sales Orders Sheet'!$Q:$Q,R$4) | S14: =AVERAGEIFS('Sales Orders Sheet'!$N:$N,'Sales Orders Sheet'!$W:$W,C14,'Sales Orders Sheet'!$Q:$Q,S$4) | T14: =AVERAGEIFS('Sales Orders Sheet'!$N:$N,'Sales Orders Sheet'!$W:$W,C14,'Sales Orders Sheet'!$Q:$Q,T$4)
C15: Ornaments | D15: =AVERAGEIFS('Sales Orders Sheet'!$O:$O,'Sales Orders Sheet'!$W:$W,C15) | E15: =AVERAGEIFS('Sales Orders Sheet'!$P:$P,'Sales Orders Sheet'!$W:$W,C15) | F15: =SUMIFS('Sales Orders Sheet'!$M:$M,'Sales Orders Sheet'!$W:$W,C15,'Sales Orders Sheet'!$Q:$Q,F$4) | G15: =SUMIFS('Sales Orders Sheet'!$M:$M,'Sales Orders Sheet'!$W:$W,C15,'Sales Orders Sheet'!$Q:$Q,G$4) | H15: =SUMIFS('Sales Orders Sheet'!$M:$M,'Sales Orders Sheet'!$W:$W,C15,'Sales Orders Sheet'!$Q:$Q,H$4) | I15: =SUMIFS('Sales Orders Sheet'!$M:$M,'Sales Orders Sheet'!$W:$W,C15,'Sales Orders Sheet'!$Q:$Q,I$4) | J15: =SUMIFS('Sales Orders Sheet'!$M:$M,'Sales Orders Sheet'!$W:$W,C15,'Sales Orders Sheet'!$Q:$Q,J$4) | K15: =SUMIFS('Sales Orders Sheet'!$T:$T,'Sales Orders Sheet'!$W:$W,C15,'Sales Orders Sheet'!$Q:$Q,K$4) | L15: =SUMIFS('Sales Orders Sheet'!$T:$T,'Sales Orders Sheet'!$W:$W,C15,'Sales Orders Sheet'!$Q:$Q,L$4) | M15: =SUMIFS('Sales Orders Sheet'!$T:$T,'Sales Orders Sheet'!$W:$W,C15,'Sales Orders Sheet'!$Q:$Q,M$4) | N15: =SUMIFS('Sales Orders Sheet'!$T:$T,'Sales Orders Sheet'!$W:$W,C15,'Sales Orders Sheet'!$Q:$Q,N$4) | O15: =SUMIFS('Sales Orders Sheet'!$T:$T,'Sales Orders Sheet'!$W:$W,C15,'Sales Orders Sheet'!$Q:$Q,O$4) | P15: =AVERAGEIFS('Sales Orders Sheet'!$N:$N,'Sales Orders Sheet'!$W:$W,C15,'Sales Orders Sheet'!$Q:$Q,P$4) | Q15: =AVERAGEIFS('Sales Orders Sheet'!$N:$N,'Sales Orders Sheet'!$W:$W,C15,'Sales Orders Sheet'!$Q:$Q,Q$4) | R15: =AVERAGEIFS('Sales Orders Sheet'!$N:$N,'Sales Orders Sheet'!$W:$W,C15,'Sales Orders Sheet'!$Q:$Q,R$4) | S15: =AVERAGEIFS('Sales Orders Sheet'!$N:$N,'Sales Orders Sheet'!$W:$W,C15,'Sales Orders Sheet'!$Q:$Q,S$4) | T15: =AVERAGEIFS('Sales Orders Sheet'!$N:$N,'Sales Orders Sheet'!$W:$W,C15,'Sales Orders Sheet'!$Q:$Q,T$4)
C16: Dining Furniture | D16: =AVERAGEIFS('Sales Orders Sheet'!$O:$O,'Sales Orders Sheet'!$W:$W,C16) | E16: =AVERAGEIFS('Sales Orders Sheet'!$P:$P,'Sales Orders Sheet'!$W:$W,C16) | F16: =SUMIFS('Sales Orders Sheet'!$M:$M,'Sales Orders Sheet'!$W:$W,C16,'Sales Orders Sheet'!$Q:$Q,F$4) | G16: =SUMIFS('Sales Orders Sheet'!$M:$M,'Sales Orders Sheet'!$W:$W,C16,'Sales Orders Sheet'!$Q:$Q,G$4) | H16: =SUMIFS('Sales Orders Sheet'!$M:$M,'Sales Orders Sheet'!$W:$W,C16,'Sales Orders Sheet'!$Q:$Q,H$4) | I16: =SUMIFS('Sales Orders Sheet'!$M:$M,'Sales Orders Sheet'!$W:$W,C16,'Sales Orders Sheet'!$Q:$Q,I$4) | J16: =SUMIFS('Sales Orders Sheet'!$M:$M,'Sales Orders Sheet'!$W:$W,C16,'Sales Orders Sheet'!$Q:$Q,J$4) | K16: =SUMIFS('Sales Orders Sheet'!$T:$T,'Sales Orders Sheet'!$W:$W,C16,'Sales Orders Sheet'!$Q:$Q,K$4) | L16: =SUMIFS('Sales Orders Sheet'!$T:$T,'Sales Orders Sheet'!$W:$W,C16,'Sales Orders Sheet'!$Q:$Q,L$4) | M16: =SUMIFS('Sales Orders Sheet'!$T:$T,'Sales Orders Sheet'!$W:$W,C16,'Sales Orders Sheet'!$Q:$Q,M$4) | N16: =SUMIFS('Sales Orders Sheet'!$T:$T,'Sales Orders Sheet'!$W:$W,C16,'Sales Orders Sheet'!$Q:$Q,N$4) | O16: =SUMIFS('Sales Orders Sheet'!$T:$T,'Sales Orders Sheet'!$W:$W,C16,'Sales Orders Sheet'!$Q:$Q,O$4) | P16: =AVERAGEIFS('Sales Orders Sheet'!$N:$N,'Sales Orders Sheet'!$W:$W,C16,'Sales Orders Sheet'!$Q:$Q,P$4) | Q16: =AVERAGEIFS('Sales Orders Sheet'!$N:$N,'Sales Orders Sheet'!$W:$W,C16,'Sales Orders Sheet'!$Q:$Q,Q$4) | R16: =AVERAGEIFS('Sales Orders Sheet'!$N:$N,'Sales Orders Sheet'!$W:$W,C16,'Sales Orders Sheet'!$Q:$Q,R$4) | S16: =AVERAGEIFS('Sales Orders Sheet'!$N:$N,'Sales Orders Sheet'!$W:$W,C16,'Sales Orders Sheet'!$Q:$Q,S$4) | T16: =AVERAGEIFS('Sales Orders Sheet'!$N:$N,'Sales Orders Sheet'!$W:$W,C16,'Sales Orders Sheet'!$Q:$Q,T$4)
... C51: Audio | D51: =AVERAGEIFS('Sales Orders Sheet'!$O:$O,'Sales Orders Sheet'!$W:$W,C51) | E51: =AVERAGEIFS('Sales Orders Sheet'!$P:$P,'Sales Orders Sheet'!$W:$W,C51) | F51: =SUMIFS('Sales Orders Sheet'!$M:$M,'Sales Orders Sheet'!$W:$W,C51,'Sales Orders Sheet'!$Q:$Q,F$4) | G51: =SUMIFS('Sales Orders Sheet'!$M:$M,'Sales Orders Sheet'!$W:$W,C51,'Sales Orders Sheet'!$Q:$Q,G$4) | H51: =SUMIFS('Sales Orders Sheet'!$M:$M,'Sales Orders Sheet'!$W:$W,C51,'Sales Orders Sheet'!$Q:$Q,H$4) | I51: =SUMIFS('Sales Orders Sheet'!$M:$M,'Sales Orders Sheet'!$W:$W,C51,'Sales Orders Sheet'!$Q:$Q,I$4) | J51: =SUMIFS('Sales Orders Sheet'!$M:$M,'Sales Orders Sheet'!$W:$W,C51,'Sales Orders Sheet'!$Q:$Q,J$4) | K51: =SUMIFS('Sales Orders Sheet'!$T:$T,'Sales Orders Sheet'!$W:$W,C51,'Sales Orders Sheet'!$Q:$Q,K$4) | L51: =SUMIFS('Sales Orders Sheet'!$T:$T,'Sales Orders Sheet'!$W:$W,C51,'Sales Orders Sheet'!$Q:$Q,L$4) | M51: =SUMIFS('Sales Orders Sheet'!$T:$T,'Sales Orders Sheet'!$W:$W,C51,'Sales Orders Sheet'!$Q:$Q,M$4) | N51: =SUMIFS('Sales Orders Sheet'!$T:$T,'Sales Orders Sheet'!$W:$W,C51,'Sales Orders Sheet'!$Q:$Q,N$4) | O51: =SUMIFS('Sales Orders Sheet'!$T:$T,'Sales Orders Sheet'!$W:$W,C51,'Sales Orders Sheet'!$Q:$Q,O$4) | P51: =AVERAGEIFS('Sales Orders Sheet'!$N:$N,'Sales Orders Sheet'!$W:$W,C51,'Sales Orders Sheet'!$Q:$Q,P$4) | Q51: =AVERAGEIFS('Sales Orders Sheet'!$N:$N,'Sales Orders Sheet'!$W:$W,C51,'Sales Orders Sheet'!$Q:$Q,Q$4) | R51: =AVERAGEIFS('Sales Orders Sheet'!$N:$N,'Sales Orders Sheet'!$W:$W,C51,'Sales Orders Sheet'!$Q:$Q,R$4) | S51: =AVERAGEIFS('Sales Orders Sheet'!$N:$N,'Sales Orders Sheet'!$W:$W,C51,'Sales Orders Sheet'!$Q:$Q,S$4) | T51: =AVERAGEIFS('Sales Orders Sheet'!$N:$N,'Sales Orders Sheet'!$W:$W,C51,'Sales Orders Sheet'!$Q:$Q,T$4)
C52: TOTAL / OVERALL | D52: =AVERAGE(D5:D51) | E52: =AVERAGE(E5:E51) | F52: =SUM(F5:F51) | G52: =SUM(G5:G51) | H52: =SUM(H5:H51) | I52: =SUM(I5:I51) | J52: =SUM(J5:J51) | K52: =SUM(K5:K51) | L52: =SUM(L5:L51) | M52: =SUM(M5:M51) | ... O52: =SUM(O5:O51) | P52: =AVERAGE(P5:P51) | Q52: =AVERAGE(Q5:Q51) | R52: =AVERAGE(R5:R51) | S52: =AVERAGE(S5:S51) | T52: =AVERAGE(T5:T51)

Sheet Sales Orders Sheet
A1: OrderNumber | B1: Sales Channel | C1: WarehouseCode | D1: ProcuredDate | E1: OrderDate | F1: ShipDate | G1: DeliveryDate | H1: CurrencyCode | I1: _SalesTeamID | J1: _CustomerID | K1: _StoreID | L1: _ProductID | M1: Order Quantity | N1: Discount Applied | O1: Unit Price | P1: Unit Cost | Q1: Order day | R1: Delivery time | S1: Stock time | T1: Order value | U1: Discount value | V1: Order gross profit | W1: Product Category (helper)
A2: SO - 000106 | B2: Online | C2: WARE-PUJ1005 | D2: 43100 | E2: 43251 | F2: 43259 | G2: 43264 | H2: USD | I2: 12 | J2: 21 | K2: 285 | L2: 1 | M2: 5 | N2: 0.05 | O2: 1038.5 | P2: 446.555 | Q2: =text(E2,"ddd") | R2: =G2-F2 | S2: =E2-D2 | T2: =O2*M2 | U2: =T2*N2 | V2: =T2-U2-(P2*M2) | W2: =VLOOKUP(L2,'Products Sheet'!$A:$B,2,FALSE)
A3: SO - 000122 | B3: In-Store | C3: WARE-PUJ1005 | D3: 43200 | E3: 43253 | F3: 43261 | G3: 43267 | H3: USD | I3: 2 | J3: 14 | K3: 282 | L3: 1 | M3: 7 | N3: 0.075 | O3: 991.6 | P3: 654.456 | Q3: =text(E3,"ddd") | R3: =G3-F3 | S3: =E3-D3 | T3: =O3*M3 | U3: =T3*N3 | V3: =T3-U3-(P3*M3) | W3: =VLOOKUP(L3,'Products Sheet'!$A:$B,2,FALSE) | X3: Total gross profit = | Z3: =sum(V2:V7992)
A4: SO - 000137 | B4: In-Store | C4: WARE-UHY1004 | D4: 43100 | E4: 43254 | F4: 43265 | G4: 43272 | H4: USD | I4: 7 | J4: 46 | K4: 256 | L4: 1 | M4: 1 | N4: 0.075 | O4: 261.3 | P4: 120.198 | Q4: =text(E4,"ddd") | R4: =G4-F4 | S4: =E4-D4 | T4: =O4*M4 | U4: =T4*N4 | V4: =T4-U4-(P4*M4) | W4: =VLOOKUP(L4,'Products Sheet'!$A:$B,2,FALSE) | X4: Max delivery time = | Z4: =max(R2:R7992)
A5: SO - 000159 | B5: Online | C5: WARE-NBV1002 | D5: 43100 | E5: 43257 | F5: 43282 | G5: 43285 | H5: USD | I5: 14 | J5: 47 | K5: 60 | L5: 1 | M5: 1 | N5: 0.4 | O5: 857.6 | P5: 686.08 | Q5: =text(E5,"ddd") | R5: =G5-F5 | S5: =E5-D5 | T5: =O5*M5 | U5: =T5*N5 | V5: =T5-U5-(P5*M5) | W5: =VLOOKUP(L5,'Products Sheet'!$A:$B,2,FALSE) | X5: Average delivery time = | Z5: =average(R2:R7992)
A6: SO - 000175 | B6: In-Store | C6: WARE-NMK1003 | D6: 43200 | E6: 43260 | F6: 43279 | G6: 43284 | H6: USD | I6: 1 | J6: 1 | K6: 107 | L6: 1 | M6: 1 | N6: 0.075 | O6: 2224.4 | P6: 1579.324 | Q6: =text(E6,"ddd") | R6: =G6-F6 | S6: =E6-D6 | T6: =O6*M6 | U6: =T6*N6 | V6: =T6-U6-(P6*M6) | W6: =VLOOKUP(L6,'Products Sheet'!$A:$B,2,FALSE) | X6: Earliest procured date = | Z6: =min(D2:D7992)
A7: SO - 000197 | B7: Online | C7: WARE-NMK1003 | D7: 43100 | E7: 43263 | F7: 43290 | G7: 43297 | H7: USD | I7: 18 | J7: 30 | K7: 90 | L7: 1 | M7: 4 | N7: 0.05 | O7: 3993.2 | P7: 2835.172 | Q7: =text(E7,"ddd") | R7: =G7-F7 | S7: =E7-D7 | T7: =O7*M7 | U7: =T7*N7 | V7: =T7-U7-(P7*M7) | W7: =VLOOKUP(L7,'Products Sheet'!$A:$B,2,FALSE) | X7: Average gross profit = | Z7: =average(V2:V7992)
A8: SO - 000205 | B8: Online | C8: WARE-NMK1003 | D8: 43200 | E8: 43264 | F8: 43276 | G8: 43277 | H8: USD | I8: 14 | J8: 14 | K8: 95 | L8: 1 | M8: 4 | N8: 0.075 | O8: 5916.1 | P8: 4673.719 | Q8: =text(E8,"ddd") | R8: =G8-F8 | S8: =E8-D8 | T8: =O8*M8 | U8: =T8*N8 | V8: =T8-U8-(P8*M8) | W8: =VLOOKUP(L8,'Products Sheet'!$A:$B,2,FALSE)
A9: SO - 000270 | B9: In-Store | C9: WARE-PUJ1005 | D9: 43200 | E9: 43270 | F9: 43288 | G9: 43295 | H9: USD | I9: 6 | J9: 27 | K9: 318 | L9: 1 | M9: 4 | N9: 0.05 | O9: 247.9 | P9: 195.841 | Q9: =text(E9,"ddd") | R9: =G9-F9 | S9: =E9-D9 | T9: =O9*M9 | U9: =T9*N9 | V9: =T9-U9-(P9*M9) | W9: =VLOOKUP(L9,'Products Sheet'!$A:$B,2,FALSE)
A10: SO - 000309 | B10: Online | C10: WARE-NMK1003 | D10: 43100 | E10: 43277 | F10: 43300 | G10: 43303 | H10: USD | I10: 15 | J10: 21 | K10: 157 | L10: 1 | M10: 2 | N10: 0.05 | O10: 1125.6 | P10: 787.92 | Q10: =text(E10,"ddd") | R10: =G10-F10 | S10: =E10-D10 | T10: =O10*M10 | U10: =T10*N10 | V10: =T10-U10-(P10*M10) | W10: =VLOOKUP(L10,'Products Sheet'!$A:$B,2,FALSE)
A11: SO - 000398 | B11: In-Store | C11: WARE-XYS1001 | D11: 43200 | E11: 43286 | F11: 43294 | G11: 43299 | H11: USD | I11: 3 | J11: 9 | K11: 58 | L11: 1 | M11: 6 | N11: 0.05 | O11: 2385.2 | P11: 1454.972 | Q11: =text(E11,"ddd") | R11: =G11-F11 | S11: =E11-D11 | T11: =O11*M11 | U11: =T11*N11 | V11: =T11-U11-(P11*M11) | W11: =VLOOKUP(L11,'Products Sheet'!$A:$B,2,FALSE)
A12: SO - 000419 | B12: Distributor | C12: WARE-NBV1002 | D12: 43200 | E12: 43289 | F12: 43316 | G12: 43325 | H12: USD | I12: 23 | J12: 47 | K12: 62 | L12: 1 | M12: 6 | N12: 0.05 | O12: 1092.1 | P12: 546.05 | Q12: =text(E12,"ddd") | R12: =G12-F12 | S12: =E12-D12 | T12: =O12*M12 | U12: =T12*N12 | V12: =T12-U12-(P12*M12) | W12: =VLOOKUP(L12,'Products Sheet'!$A:$B,2,FALSE)
A13: SO - 000464 | B13: In-Store | C13: WARE-PUJ1005 | D13: 43200 | E13: 43294 | F13: 43303 | G13: 43306 | H13: USD | I13: 4 | J13: 22 | K13: 294 | L13: 1 | M13: 2 | N13: 0.075 | O13: 3839.1 | P13: 1689.204 | Q13: =text(E13,"ddd") | R13: =G13-F13 | S13: =E13-D13 | T13: =O13*M13 | U13: =T13*N13 | V13: =T13-U13-(P13*M13) | W13: =VLOOKUP(L13,'Products Sheet'!$A:$B,2,FALSE)
A14: SO - 000505 | B14: Online | C14: WARE-UHY1004 | D14: 43200 | E14: 43299 | F14: 43313 | G14: 43317 | H14: USD | I14: 12 | J14: 21 | K14: 228 | L14: 1 | M14: 7 | N14: 0.15 | O14: 1045.2 | P14: 700.284 | Q14: =text(E14,"ddd") | R14: =G14-F14 | S14: =E14-D14 | T14: =O14*M14 | U14: =T14*N14 | V14: =T14-U14-(P14*M14) | W14: =VLOOKUP(L14,'Products Sheet'!$A:$B,2,FALSE)
A15: SO - 000513 | B15: Online | C15: WARE-XYS1001 | D15: 43200 | E15: 43300 | F15: 43326 | G15: 43334 | H15: USD | I15: 13 | J15: 35 | K15: 2 | L15: 1 | M15: 4 | N15: 0.075 | O15: 3946.3 | P15: 2012.613 | Q15: =text(E15,"ddd") | R15: =G15-F15 | S15: =E15-D15 | T15: =O15*M15 | U15: =T15*N15 | V15: =T15-U15-(P15*M15) | W15: =VLOOKUP(L15,'Products Sheet'!$A:$B,2,FALSE)
A16: SO - 000538 | B16: Online | C16: WARE-PUJ1005 | D16: 43200 | E16: 43303 | F16: 43325 | G16: 43327 | H16: USD | I16: 18 | J16: 15 | K16: 295 | L16: 1 | M16: 7 | N16: 0.075 | O16: 241.2 | P16: 185.724 | Q16: =text(E16,"ddd") | R16: =G16-F16 | S16: =E16-D16 | T16: =O16*M16 | U16: =T16*N16 | V16: =T16-U16-(P16*M16) | W16: =VLOOKUP(L16,'Products Sheet'!$A:$B,2,FALSE)
A17: SO - 000614 | B17: In-Store | C17: WARE-NMK1003 | D17: 43200 | E17: 43312 | F17: 43331 | G17: 43337 | H17: USD | I17: 12 | J17: 3 | K17: 196 | L17: 1 | M17: 7 | N17: 0.075 | O17: 1051.9 | P17: 683.735 | Q17: =text(E17,"ddd") | R17: =G17-F17 | S17: =E17-D17 | T17: =O17*M17 | U17: =T17*N17 | V17: =T17-U17-(P17*M17) | W17: =VLOOKUP(L17,'Products Sheet'!$A:$B,2,FALSE)
A18: SO - 000685 | B18: In-Store | C18: WARE-PUJ1005 | D18: 43200 | E18: 43319 | F18: 43336 | G18: 43346 | H18: USD | I18: 7 | J18: 22 | K18: 284 | L18: 1 | M18: 8 | N18: 0.1 | O18: 1855.9 | P18: 1354.807 | Q18: =text(E18,"ddd") | R18: =G18-F18 | S18: =E18-D18 | T18: =O18*M18 | U18: =T18*N18 | V18: =T18-U18-(P18*M18) | W18: =VLOOKUP(L18,'Products Sheet'!$A:$B,2,FALSE)
A19: SO - 000716 | B19: Distributor | C19: WARE-NMK1003 | D19: 43200 | E19: 43322 | F19: 43345 | G19: 43353 | H19: USD | I19: 23 | J19: 16 | K19: 156 | L19: 1 | M19: 4 | N19: 0.075 | O19: 3966.4 | P19: 2816.144 | Q19: =text(E19,"ddd") | R19: =G19-F19 | S19: =E19-D19 | T19: =O19*M19 | U19: =T19*N19 | V19: =T19-U19-(P19*M19) | W19: =VLOOKUP(L19,'Products Sheet'!$A:$B,2,FALSE)
... A7992: SO - 0008032 | B7992: Wholesale | C7992: WARE-NMK1003 | D7992: 44100 | E7992: 44189 | F7992: 44201 | G7992: 44210 | H7992: USD | I7992: 27 | J7992: 38 | K7992: 188 | L7992: 47 | M7992: 3 | N7992: 0.05 | O7992: 2311.5 | P7992: 1964.775 | Q7992: =text(E7992,"ddd") | R7992: =G7992-F7992 | S7992: =E7992-D7992 | T7992: =O7992*M7992 | U7992: =T7992*N7992 | V7992: =T7992-U7992-(P7992*M7992) | W7992: =VLOOKUP(L7992,'Products Sheet'!$A:$B,2,FALSE)

Sheet Customers Sheet
A1: _CustomerID | B1: Customer Names
A2: 1 | B2: Avon Corp
A3: 2 | B3: WakeFern
A4: 3 | B4: Elorac, Corp
A5: 4 | B5: ETUDE Ltd
A6: 5 | B6: Procter Corp
A7: 6 | B7: PEDIFIX, Corp
A8: 7 | B8: New Ltd
A9: 8 | B9: Medsep Group
A10: 9 | B10: Ei
A11: 10 | B11: 21st Ltd
A12: 11 | B12: Apollo Ltd
A13: 12 | B13: Medline
... A51: 50 | B51: Sundial

Sheet Store Locations Sheet
A1: _StoreID | B1: City Name | C1: County | D1: StateCode | E1: State | F1: Type | G1: Latitude | H1: Longitude | I1: AreaCode | J1: Population | K1: Household Income | L1: Median Income | M1: Land Area | N1: Water Area | O1: Time Zone
A2: 1 | B2: Birmingham | C2: Shelby County/Jefferson County | D2: AL | E2: Alabama | F2: City | G2: 33.52744 | H2: -86.79905 | I2: 205 | J2: 212461 | K2: 89972 | L2: 31061 | M2: 378353942 | N2: 6591013 | O2: America/Chicago
A3: 2 | B3: Huntsville | C3: Limestone County/Madison County | D3: AL | E3: Alabama | F3: City | G3: 34.69901 | H3: -86.67298 | I3: 256 | J3: 190582 | K3: 78554 | L3: 48775 | M3: 552604579 | N3: 3452021 | O3: America/Chicago
A4: 3 | B4: Mobile | C4: Mobile County | D4: AL | E4: Alabama | F4: City | G4: 30.69436 | H4: -88.04305 | I4: 251 | J4: 194288 | K4: 76170 | L4: 38776 | M4: 361044263 | N4: 105325210 | O4: America/Chicago
A5: 4 | B5: Montgomery | C5: Montgomery County | D5: AL | E5: Alabama | F5: City | G5: 32.36681 | H5: -86.29997 | I5: 334 | J5: 200602 | K5: 79866 | L5: 42927 | M5: 413985435 | N5: 4411954 | O5: America/Chicago
A6: 5 | B6: Little Rock | C6: Pulaski County | D6: AR | E6: Arkansas | F6: City | G6: 34.74648 | H6: -92.28959 | I6: 501 | J6: 197992 | K6: 79902 | L6: 46085 | M6: 307398785 | N6: 6758644 | O6: America/Chicago
A7: 6 | B7: Chandler | C7: Maricopa County | D7: AZ | E7: Arizona | F7: City | G7: 33.30616 | H7: -111.84125 | I7: 480 | J7: 260828 | K7: 88973 | L7: 72695 | M7: 168153308 | N7: 260378 | O7: America/Phoenix
A8: 7 | B8: Gilbert | C8: Maricopa County | D8: AZ | E8: Arizona | F8: Town | G8: 33.35283 | H8: -111.78903 | I8: 480 | J8: 247542 | K8: 73617 | L8: 82424 | M8: 176124143 | N8: 510475 | O8: America/Phoenix
A9: 8 | B9: Glendale | C9: Maricopa County | D9: AZ | E9: Arizona | F9: City | G9: 33.53865 | H9: -112.18599 | I9: 623 | J9: 240126 | K9: 79152 | L9: 46776 | M9: 153029354 | N9: 1003996 | O9: America/Phoenix
A10: 9 | B10: Mesa | C10: Maricopa County | D10: AZ | E10: Arizona | F10: City | G10: 33.42227 | H10: -111.82264 | I10: 480 | J10: 471825 | K10: 168914 | L10: 48809 | M10: 357097953 | N10: 1950781 | O10: America/Phoenix
A11: 10 | B11: Peoria | C11: Maricopa County/Yavapai County | D11: AZ | E11: Arizona | F11: City | G11: 33.7862 | H11: -112.30801 | I11: 928 | J11: 171237 | K11: 58588 | L11: 65314 | M11: 455011748 | N11: 8864869 | O11: America/Phoenix
A12: 11 | B12: Phoenix | C12: Maricopa County | D12: AZ | E12: Arizona | F12: City | G12: 33.44838 | H12: -112.07404 | I12: 602 | J12: 1563025 | K12: 525610 | L12: 47326 | M12: 1340692038 | N12: 3247104 | O12: America/Phoenix
A13: 12 | B13: Scottsdale | C13: Maricopa County | D13: AZ | E13: Arizona | F13: City | G13: 33.50921 | H13: -111.89903 | I13: 480 | J13: 236839 | K13: 102424 | L13: 73288 | M13: 476410748 | N13: 1220280 | O13: America/Phoenix
... A368: 367 | B368: Milwaukee | C368: Milwaukee County/Washington County/Waukesha County | D368: WI | E368: Wisconsin | F368: City | G368: 43.06335 | H368: -87.9667 | I368: 414 | J368: 600155 | K368: 230807 | L368: 35958 | M368: 249128870 | N368: 1720458 | O368: America/Chicago

Sheet Products Sheet
A1: _ProductID | B1: Product Name
A2: 1 | B2: Cookware
A3: 2 | B3: Photo Frames
A4: 3 | B4: Table Lamps
A5: 4 | B5: Serveware
A6: 5 | B6: Bathroom Furniture
A7: 6 | B7: Computers
A8: 7 | B8: Dinnerware
A9: 8 | B9: Cocktail Glasses
A10: 9 | B10: Baseball
A11: 10 | B11: Blankets
A12: 11 | B12: Ornaments
A13: 12 | B13: Dining Furniture
... A48: 47 | B48: Audio

Sheet Regions Sheet
A1: StateCode | B1: State | C1: Region
A2: AL | B2: Alabama | C2: South
A3: AR | B3: Arkansas | C3: South
A4: AZ | B4: Arizona | C4: West
A5: CA | B5: California | C5: West
A6: CO | B6: Colorado | C6: West
A7: CT | B7: Connecticut | C7: Northeast
A8: DC | B8: District of Columbia | C8: South
A9: DE | B9: Delaware | C9: South
A10: FL | B10: Florida | C10: South
A11: GA | B11: Georgia | C11: South
A12: HI | B12: Hawaii | C12: West
... A49: WY | B49: Wyoming | C49: West

Sheet Sales Team Sheet
A1: _SalesTeamID | B1: Sales Team | C1: Region
A2: 1 | B2: Adam Hernandez | C2: Northeast
A3: 2 | B3: Keith Griffin | C3: Northeast
A4: 3 | B4: Jerry Green | C4: West
A5: 4 | B5: Chris Armstrong | C5: Northeast
A6: 5 | B6: Stephen Payne | C6: South
A7: 6 | B7: Joshua Bennett | C7: Northeast
A8: 7 | B8: Shawn Cook | C8: Midwest
A9: 8 | B9: George Lewis | C9: West
A10: 9 | B10: Joshua Ryan | C10: Midwest
A11: 10 | B11: Jonathan Hawkins | C11: West
A12: 11 | B12: Joshua Little | C12: South
A13: 12 | B13: Carl Nguyen | C13: Midwest
... A29: 28 | B29: Carlos Miller | C29: West
